{"isValid":true,"resultCode":0,"itemList":[{"itemId":3702,"itemStock":56,"totalTrades":228384,"basePrice":720000},{"itemId":3703,"itemStock":0,"totalTrades":338420,"basePrice":1170000},{"itemId":3718,"itemStock":97,"totalTrades":245133,"basePrice":305000},{"itemId":3719,"itemStock":7028,"totalTrades":2826036,"basePrice":995000},{"itemId":3731,"itemStock":0,"totalTrades":26673,"basePrice":391000},{"itemId":3732,"itemStock":10,"totalTrades":37938,"basePrice":1140000},{"itemId":3741,"itemStock":0,"totalTrades":32606,"basePrice":400000},{"itemId":3742,"itemStock":155,"totalTrades":133253,"basePrice":730000},{"itemId":12831,"itemStock":0,"totalTrades":475237,"basePrice":273000},{"itemId":16102,"itemStock":18892,"totalTrades":11086322,"basePrice":5050},{"itemId":16103,"itemStock":10026,"totalTrades":8350335,"basePrice":10400},{"itemId":16104,"itemStock":8893,"totalTrades":7166357,"basePrice":14600},{"itemId":16106,"itemStock":22,"totalTrades":138655,"basePrice":47700},{"itemId":16107,"itemStock":204,"totalTrades":1162262,"basePrice":4730},{"itemId":16108,"itemStock":23,"totalTrades":647635,"basePrice":9600},{"itemId":16110,"itemStock":138,"totalTrades":88945,"basePrice":67000},{"itemId":16111,"itemStock":153,"totalTrades":302955,"basePrice":26300},{"itemId":16112,"itemStock":132,"totalTrades":168434,"basePrice":119000},{"itemId":16114,"itemStock":88,"totalTrades":100278,"basePrice":75000},{"itemId":16115,"itemStock":44,"totalTrades":250622,"basePrice":97000},{"itemId":16116,"itemStock":14,"totalTrades":182186,"basePrice":105000},{"itemId":16118,"itemStock":88,"totalTrades":212451,"basePrice":79000},{"itemId":16119,"itemStock":88,"totalTrades":766086,"basePrice":107000},{"itemId":16120,"itemStock":101,"totalTrades":522061,"basePrice":266000},{"itemId":16122,"itemStock":164,"totalTrades":83576,"basePrice":20900},{"itemId":16123,"itemStock":21,"totalTrades":324380,"basePrice":79000},{"itemId":16124,"itemStock":146,"totalTrades":200393,"basePrice":49800},{"itemId":16126,"itemStock":31,"totalTrades":249946,"basePrice":69000},{"itemId":16127,"itemStock":220,"totalTrades":602835,"basePrice":7550},{"itemId":16128,"itemStock":3953,"totalTrades":744125,"basePrice":9000},{"itemId":16147,"itemStock":1814,"totalTrades":399187,"basePrice":1500},{"itemId":16150,"itemStock":1,"totalTrades":55082,"basePrice":2630},{"itemId":16151,"itemStock":0,"totalTrades":1581794,"basePrice":38800},{"itemId":16152,"itemStock":9,"totalTrades":316139,"basePrice":496000},{"itemId":16153,"itemStock":0,"totalTrades":363439,"basePrice":9300000},{"itemId":16154,"itemStock":3990,"totalTrades":34372,"basePrice":9000},{"itemId":16155,"itemStock":149,"totalTrades":76310,"basePrice":197000},{"itemId":16157,"itemStock":107,"totalTrades":567602,"basePrice":125000},{"itemId":16158,"itemStock":54,"totalTrades":480584,"basePrice":84500},{"itemId":16159,"itemStock":133,"totalTrades":131766,"basePrice":187000},{"itemId":16160,"itemStock":24,"totalTrades":104956,"basePrice":360000},{"itemId":16161,"itemStock":78,"totalTrades":242531,"basePrice":492000},{"itemId":16162,"itemStock":0,"totalTrades":2652805,"basePrice":1260000},{"itemId":16163,"itemStock":0,"totalTrades":866310,"basePrice":1310000},{"itemId":16164,"itemStock":0,"totalTrades":79091,"basePrice":2270000},{"itemId":16165,"itemStock":6,"totalTrades":190613,"basePrice":1910000},{"itemId":16167,"itemStock":0,"totalTrades":118075,"basePrice":1060000},{"itemId":16168,"itemStock":126,"totalTrades":339322,"basePrice":1840000},{"itemId":16479,"itemStock":28,"totalTrades":9816,"basePrice":198000000},{"itemId":16481,"itemStock":11,"totalTrades":5265,"basePrice":183000000},{"itemId":16482,"itemStock":5,"totalTrades":3610,"basePrice":160000000},{"itemId":16486,"itemStock":2,"totalTrades":703,"basePrice":115000000},{"itemId":16487,"itemStock":37,"totalTrades":14965,"basePrice":192000000},{"itemId":16540,"itemStock":1,"totalTrades":3117,"basePrice":8800000},{"itemId":16805,"itemStock":0,"totalTrades":1690,"basePrice":11200},{"itemId":16806,"itemStock":0,"totalTrades":5460,"basePrice":182000},{"itemId":16807,"itemStock":0,"totalTrades":72009,"basePrice":560000},{"itemId":16808,"itemStock":0,"totalTrades":28839,"basePrice":1110000},{"itemId":16809,"itemStock":0,"totalTrades":455,"basePrice":7200},{"itemId":16810,"itemStock":0,"totalTrades":3560,"basePrice":186000},{"itemId":16811,"itemStock":0,"totalTrades":22312,"basePrice":560000},{"itemId":16812,"itemStock":0,"totalTrades":6964,"basePrice":1120000},{"itemId":16813,"itemStock":0,"totalTrades":219,"basePrice":9400},{"itemId":16814,"itemStock":0,"totalTrades":5354,"basePrice":178000},{"itemId":16815,"itemStock":0,"totalTrades":19188,"basePrice":555000},{"itemId":16816,"itemStock":0,"totalTrades":11101,"basePrice":1090000},{"itemId":16817,"itemStock":0,"totalTrades":337,"basePrice":8650},{"itemId":16818,"itemStock":6,"totalTrades":5813,"basePrice":186000},{"itemId":16819,"itemStock":9,"totalTrades":27617,"basePrice":560000},{"itemId":16820,"itemStock":0,"totalTrades":18317,"basePrice":1120000},{"itemId":16821,"itemStock":4,"totalTrades":1666,"basePrice":7950},{"itemId":16822,"itemStock":0,"totalTrades":9099,"basePrice":186000},{"itemId":16823,"itemStock":0,"totalTrades":14514,"basePrice":560000},{"itemId":16824,"itemStock":0,"totalTrades":6151,"basePrice":1120000},{"itemId":16825,"itemStock":0,"totalTrades":297,"basePrice":12700},{"itemId":16826,"itemStock":0,"totalTrades":2054,"basePrice":185000},{"itemId":16827,"itemStock":80,"totalTrades":31656,"basePrice":500000},{"itemId":16828,"itemStock":14,"totalTrades":24703,"basePrice":1080000},{"itemId":16829,"itemStock":24,"totalTrades":713999,"basePrice":20000},{"itemId":16830,"itemStock":12854,"totalTrades":1053200,"basePrice":20000},{"itemId":16831,"itemStock":317,"totalTrades":670142,"basePrice":189000},{"itemId":16832,"itemStock":151,"totalTrades":303306,"basePrice":20000},{"itemId":16833,"itemStock":179,"totalTrades":473063,"basePrice":457000},{"itemId":16834,"itemStock":172,"totalTrades":356701,"basePrice":48100},{"itemId":16847,"itemStock":6,"totalTrades":2860,"basePrice":177000000},{"itemId":49804,"itemStock":0,"totalTrades":23471,"basePrice":6000000},{"itemId":49805,"itemStock":0,"totalTrades":808,"basePrice":14000000},{"itemId":49808,"itemStock":0,"totalTrades":148,"basePrice":3990000},{"itemId":56133,"itemStock":20,"totalTrades":33495,"basePrice":1090000},{"itemId":56220,"itemStock":0,"totalTrades":103,"basePrice":219000000},{"itemId":705154,"itemStock":0,"totalTrades":35392,"basePrice":850000},{"itemId":705155,"itemStock":1,"totalTrades":16156,"basePrice":8700000},{"itemId":705156,"itemStock":60,"totalTrades":20734,"basePrice":237000000},{"itemId":720501,"itemStock":0,"totalTrades":277,"basePrice":120000000},{"itemId":720502,"itemStock":0,"totalTrades":578,"basePrice":121000000},{"itemId":720503,"itemStock":2,"totalTrades":1571,"basePrice":157000000},{"itemId":720504,"itemStock":0,"totalTrades":145,"basePrice":133000000},{"itemId":720505,"itemStock":0,"totalTrades":98,"basePrice":134000000},{"itemId":720506,"itemStock":4,"totalTrades":1141,"basePrice":144000000},{"itemId":720508,"itemStock":2,"totalTrades":2642,"basePrice":8750000},{"itemId":720509,"itemStock":0,"totalTrades":2041,"basePrice":8750000},{"itemId":720510,"itemStock":0,"totalTrades":1041,"basePrice":8800000},{"itemId":720511,"itemStock":0,"totalTrades":4816,"basePrice":8700000},{"itemId":720512,"itemStock":0,"totalTrades":1756,"basePrice":8750000},{"itemId":720513,"itemStock":0,"totalTrades":1690,"basePrice":8750000},{"itemId":720514,"itemStock":0,"totalTrades":2782,"basePrice":8750000},{"itemId":720515,"itemStock":3,"totalTrades":3664,"basePrice":8750000},{"itemId":720516,"itemStock":0,"totalTrades":1244,"basePrice":8800000},{"itemId":720517,"itemStock":56,"totalTrades":7238,"basePrice":5050000},{"itemId":720518,"itemStock":0,"totalTrades":3436,"basePrice":8700000},{"itemId":720519,"itemStock":2,"totalTrades":12866,"basePrice":600000},{"itemId":720520,"itemStock":0,"totalTrades":22036,"basePrice":600000},{"itemId":720521,"itemStock":0,"totalTrades":17180,"basePrice":600000},{"itemId":720522,"itemStock":0,"totalTrades":6210,"basePrice":580000},{"itemId":720523,"itemStock":0,"totalTrades":32350,"basePrice":590000},{"itemId":720524,"itemStock":0,"totalTrades":12207,"basePrice":600000},{"itemId":720525,"itemStock":0,"totalTrades":8597,"basePrice":600000},{"itemId":720526,"itemStock":0,"totalTrades":14445,"basePrice":595000},{"itemId":720527,"itemStock":0,"totalTrades":19831,"basePrice":600000},{"itemId":720528,"itemStock":0,"totalTrades":6979,"basePrice":595000},{"itemId":720529,"itemStock":0,"totalTrades":4643,"basePrice":600000},{"itemId":720530,"itemStock":0,"totalTrades":18143,"basePrice":600000}]}